LICENSE
README.md
setup.py
tk_datepicker/__init__.py
tk_datepicker/tk_datepicker.py
tk_datepicker.egg-info/PKG-INFO
tk_datepicker.egg-info/SOURCES.txt
tk_datepicker.egg-info/dependency_links.txt
tk_datepicker.egg-info/top_level.txt