Metadata-Version: 2.1
Name: tk-datepicker
Version: 0.0.2
Summary: Calendar for Tkinter module
Home-page: UNKNOWN
Author: QuantumaStelata
Author-email: <quantumastelata@gmail.com>
License: UNKNOWN
Keywords: python,tk,tkinter,calendar,tk_datepicker,pytk
Platform: UNKNOWN
Classifier: Programming Language :: Python :: 3
License-File: LICENSE
